mdmindmap/__init__.py
mdmindmap/__main__.py
mdmindmap/cli.py
mdmindmap/core.py
mdmindmap/server.py
mdmindmap-0.1.0.dist-info/METADATA
mdmindmap-0.1.0.dist-info/WHEEL
mdmindmap-0.1.0.dist-info/entry_points.txt
mdmindmap-0.1.0.dist-info/top_level.txt
mdmindmap-0.1.0.dist-info/RECORD
