Metadata-Version: 2.4
Name: mdmindmap
Version: 0.1.0
Summary: Generate interactive mindmaps from Markdown with expand/collapse and editing support
Author-email: Your Name <you@example.com>
License: MIT
Requires-Dist: markdown
Requires-Dist: pyyaml
Requires-Dist: flask
